[1,["9erH6Np3tI6ailRY45lT9H","94bmU7WMpPhYxS35xwoUJS","12f7c0560","b6glM11/ZA8qdnG6Ao6WZP","29FYIk+N1GYaeWH/q1NxQO","f6MdXFVlJN96Z90eZ5twNC"],["node","_spriteFrame","_textureSetter","root","_N$target","data","_N$normalSprite","_N$disabledSprite","_defaultClip"],[["cc.Node",["_name","_opacity","_components","_prefab","_contentSize","_parent","_children","_trs","_color"],1,9,4,5,1,2,7,5],["cc.Sprite",["_isTrimmedMode","_sizeMode","_type","node","_spriteFrame"],0,1,6],["cc.Button",["_N$transition","node","_N$normalColor","_N$target","clickEvents","_N$normalSprite","_N$disabledSprite"],2,1,5,1,9,6,6],"cc.SpriteFrame",["cc.Prefab",["_name"],2],["8dc998/NDVHg6JuAoBzVsXM",["node"],3,1],["cc.Animation",["playOnLoad","node","_clips","_defaultClip"],2,1,3,6],["cc.PrefabInfo",["fileId","root"],2,1],["cc.ClickEvent",["_componentId","handler","target"],1,1]],[[7,0,1,2],[4,0,2],[0,0,6,2,3,4,2],[0,0,1,5,2,3,8,4,3],[0,0,5,6,2,3,4,7,2],[0,0,5,2,3,4,7,2],[5,0,1],[6,0,1,2,3,2],[1,1,3,4,2],[1,0,3,4,2],[1,2,0,3,4,3],[2,1,2,3,1],[2,0,1,4,2,5,6,2],[8,0,1,2,3]],[[[{"name":"GameRuleBg","rect":[3,3,1004,565],"offset":[0,0],"originalSize":[1004,565],"capInsets":[0,0,0,0]}],[3],0,[0],[2],[2]],[[[1,"CompetitionRoomRule"],[2,"Layer",[-4,-5],[[6,-2],[7,true,-3,[6],5]],[0,"2e/CCSGq1IwI3p4TMof3n/",-1],[5,1136,640]],[3,"sprite_splash",118,1,[[8,0,-6,0],[11,-8,[4,4292269782],-7]],[0,"ecqklOTzVEibcCdLHov8ve",1],[4,4278190080],[5,1704,960]],[4,"bg",1,[-10],[[9,false,-9,4]],[0,"07fUxgfdtBcbWmioq6A0Ge",1],[5,1004,565],[0,0,0,0,0,0,1,0.9,0.9,1]],[5,"btnClose",3,[[12,3,-11,[[13,"8dc998/NDVHg6JuAoBzVsXM","onBack",1]],[4,4292269782],1,2],[10,1,false,-12,3]],[0,"93vXKeVG1HCrCD2SbCC2kf",1],[5,91,75],[433,251,0,0,0,0,1,1,1,1]]],0,[0,3,1,0,0,1,0,0,1,0,-1,2,0,-2,3,0,0,2,0,4,2,0,0,2,0,0,3,0,-1,4,0,0,4,0,0,4,0,5,1,12],[0,0,0,0,0,0,0],[1,6,7,1,1,8,-1],[3,0,4,0,5,1,1]]]]