[1,["4bYA9QC2dNNrt1b6omPwz4","63jn6xIvFGOpWlrrZqOjEA","39HyaFSO1BaIdNtFeHuaEJ","86r3llIzNFoaGsC0NRko4B","f0Vj1NOwdKmYRADlKo5sTc","8cZJL8itdAgJwkd8239LaX","4eJWJgulRN76Ag6S/YohwN","4dDbLriYVEk47+WCL8FE4S","1brlnblUVF6oafRTpKG7My","1bRE8MjFFC2JXel6kcdZ74","8e25Ea+z5Gt5yRaVUuo3Gs","70lX2jkk5AxrcEb3cHvmIK","c9sApkmSVPRKo2ov7z5eVJ","16mQZ/OD9GIIpaf3w8gNNE","d6pXZ/pTZNDr076v7wFCHk","668U7S06ZK/5OnRBeyaTD3","60mLJbIBFJ97GfIw2Kl91c","94oWddUslCs61VX/UBBDTR","e7uO2it4pBebt8moy+QrFN","f8+tnyYaNMkqL4Dv8e63SR","8fM3DfIj1Nw5ur2pqt0zG7"],["_textureSetter","payline_00","payline_01","payline_02","payline_03","payline_04","payline_05","payline_06","payline_07","payline_08","payline_09","payline_10","payline_11","payline_12","payline_13","payline_14","payline_15","payline_16","payline_17","payline_18","payline_19"],["cc.SpriteFrame",["cc.SpriteAtlas",["_name","_spriteFrames"],2,11]],[[1,0,1,2]],[[[[0,"payline.plist",[{},"payline_00",6,0,"payline_01",6,1,"payline_02",6,2,"payline_03",6,3,"payline_04",6,4,"payline_05",6,5,"payline_06",6,6,"payline_07",6,7,"payline_08",6,8,"payline_09",6,9,"payline_10",6,10,"payline_11",6,11,"payline_12",6,12,"payline_13",6,13,"payline_14",6,14,"payline_15",6,15,"payline_16",6,16,"payline_17",6,17,"payline_18",6,18,"payline_19",6,19]]],0,0,[0,0,0,0,0,0,0,0,0,0,0,0,0,0,0,0,0,0,0,0],[1,2,3,4,5,6,7,8,9,10,11,12,13,14,15,16,17,18,19,20],[1,2,3,4,5,6,7,8,9,10,11,12,13,14,15,16,17,18,19,20]],[[{"name":"payline_12","rect":[0,420,866,35],"offset":[0,0],"originalSize":[866,35],"capInsets":[0,0,0,0]}],[0],0,[0],[0],[0]],[[{"name":"payline_08","rect":[0,280,866,35],"offset":[0,0],"originalSize":[866,35],"capInsets":[0,0,0,0]}],[0],0,[0],[0],[0]],[[{"name":"payline_07","rect":[0,245,866,35],"offset":[0,0],"originalSize":[866,35],"capInsets":[0,0,0,0]}],[0],0,[0],[0],[0]],[[{"name":"payline_01","rect":[0,35,866,35],"offset":[0,0],"originalSize":[866,35],"capInsets":[0,0,0,0]}],[0],0,[0],[0],[0]],[[{"name":"payline_06","rect":[0,210,866,35],"offset":[0,0],"originalSize":[866,35],"capInsets":[0,0,0,0]}],[0],0,[0],[0],[0]],[[{"name":"payline_05","rect":[0,175,866,35],"offset":[0,0],"originalSize":[866,35],"capInsets":[0,0,0,0]}],[0],0,[0],[0],[0]],[[{"name":"payline_15","rect":[0,525,866,35],"offset":[0,0],"originalSize":[866,35],"capInsets":[0,0,0,0]}],[0],0,[0],[0],[0]],[[{"name":"payline_00","rect":[0,0,866,35],"offset":[0,0],"originalSize":[866,35],"capInsets":[0,0,0,0]}],[0],0,[0],[0],[0]],[[{"name":"payline_14","rect":[0,490,866,35],"offset":[0,0],"originalSize":[866,35],"capInsets":[0,0,0,0]}],[0],0,[0],[0],[0]],[[{"name":"payline_10","rect":[0,350,866,35],"offset":[0,0],"originalSize":[866,35],"capInsets":[0,0,0,0]}],[0],0,[0],[0],[0]],[[{"name":"payline_02","rect":[0,70,866,35],"offset":[0,0],"originalSize":[866,35],"capInsets":[0,0,0,0]}],[0],0,[0],[0],[0]],[[{"name":"payline_04","rect":[0,140,866,35],"offset":[0,0],"originalSize":[866,35],"capInsets":[0,0,0,0]}],[0],0,[0],[0],[0]],[[{"name":"payline_09","rect":[0,315,866,35],"offset":[0,0],"originalSize":[866,35],"capInsets":[0,0,0,0]}],[0],0,[0],[0],[0]],[[{"name":"payline_19","rect":[0,665,866,35],"offset":[0,0],"originalSize":[866,35],"capInsets":[0,0,0,0]}],[0],0,[0],[0],[0]],[[{"name":"payline_16","rect":[0,560,866,35],"offset":[0,0],"originalSize":[866,35],"capInsets":[0,0,0,0]}],[0],0,[0],[0],[0]],[[{"name":"payline_11","rect":[0,385,866,35],"offset":[0,0],"originalSize":[866,35],"capInsets":[0,0,0,0]}],[0],0,[0],[0],[0]],[[{"name":"payline_13","rect":[0,455,866,35],"offset":[0,0],"originalSize":[866,35],"capInsets":[0,0,0,0]}],[0],0,[0],[0],[0]],[[{"name":"payline_17","rect":[0,595,866,35],"offset":[0,0],"originalSize":[866,35],"capInsets":[0,0,0,0]}],[0],0,[0],[0],[0]],[[{"name":"payline_03","rect":[0,105,866,35],"offset":[0,0],"originalSize":[866,35],"capInsets":[0,0,0,0]}],[0],0,[0],[0],[0]],[[{"name":"payline_18","rect":[0,630,866,35],"offset":[0,0],"originalSize":[866,35],"capInsets":[0,0,0,0]}],[0],0,[0],[0],[0]]]]